Workbook

Sheet Banking Capability Map
A1: Level | B1: Capability Name | C1: Parent Capability | D1: Capability Description | E1: Industry Adoption Level | F1: AI Infused Capability | G1: Maturity Level | H1: Key Technologies Involved | I1: Capability Function Category
A2: L1 | B2: Payment Management | C2: - | D2: The enterprise-wide ability to initiate, process, route, clear, settle, and reconcile all forms of monetary transactions across retail, commercial, and interbank channels. This capability encompasses the full payment lifecycle from instruction origination through final settlement, including compliance screening, exception handling, and reporting. It serves as a critical value-enabling domain that underpins virtually all banking products and customer interactions, supporting domestic and cross-border flows across multiple currencies, payment schemes, and regulatory jurisdictions. | E2: High | F2: True | G2: Mature | H2: ISO 20022, SWIFT gpi, FedNow, RTP, SEPA, ACH, Mastercard/Visa Networks, Ripple, Blockchain DLT | I2: Payment Infrastructure
A3: L2 | B3: Payment Processing | C3: Payment Management | D3: The ability to receive, validate, enrich, route, and execute payment instructions across all supported payment types including credit transfers, direct debits, card transactions, and digital wallet payments. This capability handles message parsing, format transformation, sanctions and fraud screening, routing logic, and execution confirmation. It operates in both batch and real-time modes and must support STP (straight-through processing) rates above 95% for competitive institutions. | E3: High | F3: True | G3: Mature | H3: Payment hubs (Volante, Finastra GPP, ACI Worldwide), ISO 20022 message standards, SWIFT MX/MT, API gateways | I3: Payment Infrastructure
A4: L3 | B4: Real-Time Payment Processing | C4: Payment Processing | D4: The ability to process and settle payment instructions within seconds on a 24/7/365 basis with immediate availability of funds to the beneficiary. Supports instant credit transfers, request-to-pay flows, and real-time confirmation/notification to both payer and payee. Requires always-on infrastructure with sub-second latency targets and 99.99% uptime SLAs. | E4: High | F4: True | G4: Growing | H4: FedNow, RTP (The Clearing House), SEPA Instant, UPI, Faster Payments, ISO 20022, Cloud-native payment engines | I4: Payment Infrastructure
A5: L4 | B5: Instant Credit Transfer | C5: Real-Time Payment Processing | D5: The granular ability to execute an irrevocable credit transfer from payer to payee account with funds available within 10 seconds, including real-time validation of beneficiary account status, balance sufficiency check, sanctions screening, and immediate posting to both accounts with confirmation notifications. | E5: High | F5: True | G5: Growing | H5: FedNow Instant Payments, TCH RTP, TIPS (TARGET Instant Payment Settlement), NPP (Australia) | I5: Payment Infrastructure
A6: L4 | B6: Request to Pay | C6: Real-Time Payment Processing | D6: The ability to generate, transmit, and manage payment requests from payee to payer through real-time payment rails, enabling the payer to approve, decline, or schedule payment. Supports both consumer and business use cases including bill presentment, invoice payment, and point-of-sale transactions. | E6: Medium | F6: False | G6: Emerging | H6: EPC Request to Pay scheme, Open Banking APIs, PSD2/PSD3 frameworks | I6: Payment Infrastructure
A7: L3 | B7: Batch Payment Processing | C7: Payment Processing | D7: The ability to aggregate, validate, and process large volumes of payment instructions in scheduled batch cycles, typically for payroll, vendor payments, government disbursements, and recurring billing. Includes file ingestion, format validation, duplicate detection, and batch-level reporting and reconciliation. | E7: High | F7: False | G7: Saturated | H7: ACH (NACHA), BACS, BECS, SEPA Core/B2B Direct Debit, mainframe batch processing, ETL tools | I7: Payment Infrastructure
A8: L4 | B8: Payroll Processing | C8: Batch Payment Processing | D8: The ability to process employer-originated bulk salary payments including net pay distribution, tax withholding remittances, benefits deductions, and multi-bank payroll disbursement with same-day or next-day value dating. | E8: High | F8: False | G8: Saturated | H8: ACH payroll origination, NACHA file formats, SAP/Workday payroll integration, SFTP secure file transfer | I8: Payment Infrastructure
A9: L4 | B9: Direct Debit Processing | C9: Batch Payment Processing | D9: The ability to process creditor-initiated collection instructions against debtor accounts based on pre-authorized mandates, including mandate management, pre-notification, collection scheduling, return and refund handling, and R-transaction processing. | E9: High | F9: False | G9: Saturated | H9: SEPA Direct Debit Core/B2B, ACH debit origination, BACS Direct Debit, Mandate management systems | I9: Payment Infrastructure
A10: L3 | B10: Card Payment Processing | C10: Payment Processing | D10: The ability to authorize, clear, and settle card-based payment transactions across credit, debit, and prepaid card products for both issuing and acquiring sides. Includes real-time authorization decisioning, EMV chip and contactless processing, tokenized transaction handling, 3D Secure authentication, and chargeback/dispute lifecycle management. | E10: High | F10: True | G10: Mature | H10: Visa/Mastercard networks, EMV specifications, Apple Pay/Google Pay tokenization, PCI DSS, 3DS2 protocol, ISO 8583 | I10: Payment Infrastructure
A11: L4 | B11: Card Authorization | C11: Card Payment Processing | D11: The ability to receive and process real-time authorization requests from acquirers or merchants, validate card status, check available credit/balance, apply fraud scoring, enforce velocity limits, and return approval or decline decisions within sub-second timeframes. | E11: High | F11: True | G11: Mature | H11: ISO 8583, Visa VTS, Mastercard MDES, Neural network fraud scoring, Real-time decisioning engines | I11: Payment Infrastructure
A12: L4 | B12: Card Clearing and Settlement | C12: Card Payment Processing | D12: The ability to process end-of-day clearing files from card networks, match authorizations to presentments, calculate net settlement positions, apply interchange fees, and execute interbank fund transfers to complete the card transaction lifecycle. | E12: High | F12: False | G12: Saturated | H12: VisaNet, Mastercard Banknet, Clearing file processing, CHIPS/Fedwire for settlement | I12: Payment Infrastructure
... A175: L2 | B175: Trade Compliance | C175: Trade Finance and Supply Chain Finance | D175: The ability to ensure trade transactions comply with export control regulations, trade sanctions, dual-use goods restrictions, and anti-boycott rules. Includes automated trade compliance screening, license management, and regulatory reporting for cross-border trade. | E175: High | F175: True | G175: Growing | H175: Trade compliance screening (Dow Jones, Fircosoft), Export control databases (BIS, OFAC), Dual-use goods classification, Sanctions screening | I175: Security & Compliance

Sheet Summary Dashboard
A1: Banking Capability Map - Summary Dashboard
A3: Metric | B3: Count
A4: Total Capabilities | B4: =COUNTA('Banking Capability Map'!A2:A175) -> 174
A5: L1 Capabilities | B5: =COUNTIF('Banking Capability Map'!A2:A175,"L1") -> 14
A6: L2 Capabilities | B6: =COUNTIF('Banking Capability Map'!A2:A175,"L2") -> 60
A7: L3 Capabilities | B7: =COUNTIF('Banking Capability Map'!A2:A175,"L3") -> 88
A8: L4 Capabilities | B8: =COUNTIF('Banking Capability Map'!A2:A175,"L4") -> 12
A10: AI Infused Capabilities | B10: =COUNTIF('Banking Capability Map'!F2:F175,"True") -> 140
A11: Non-AI Capabilities | B11: =COUNTIF('Banking Capability Map'!F2:F175,"False") -> 34
A13: Maturity Distribution | B13: Count
A14: Emerging | B14: =COUNTIF('Banking Capability Map'!G2:G175,"Emerging") -> 13
A15: Growing | B15: =COUNTIF('Banking Capability Map'!G2:G175,"Growing") -> 67
A16: Mature | B16: =COUNTIF('Banking Capability Map'!G2:G175,"Mature") -> 83
A17: Saturated | B17: =COUNTIF('Banking Capability Map'!G2:G175,"Saturated") -> 11
A19: Function Category Distribution | B19: Count
A20: Payment Infrastructure | B20: =COUNTIF('Banking Capability Map'!I2:I175,"Payment Infrastructure") -> 27
A21: Core Banking Systems | B21: =COUNTIF('Banking Capability Map'!I2:I175,"Core Banking Systems") -> 31
A22: Customer & Digital Experience | B22: =COUNTIF('Banking Capability Map'!I2:I175,"Customer & Digital Experience") -> 13
A23: Risk Management | B23: =COUNTIF('Banking Capability Map'!I2:I175,"Risk Management") -> 17
A24: Security & Compliance | B24: =COUNTIF('Banking Capability Map'!I2:I175,"Security & Compliance") -> 22
A25: Data & Analytics | B25: =COUNTIF('Banking Capability Map'!I2:I175,"Data & Analytics") -> 16
A26: Treasury & Capital Markets | B26: =COUNTIF('Banking Capability Map'!I2:I175,"Treasury & Capital Markets") -> 11
A27: Enterprise Services | B27: =COUNTIF('Banking Capability Map'!I2:I175,"Enterprise Services") -> 16
A28: Internal Operations | B28: =COUNTIF('Banking Capability Map'!I2:I175,"Internal Operations") -> 12
A29: Partner Ecosystem | B29: =COUNTIF('Banking Capability Map'!I2:I175,"Partner Ecosystem") -> 9

Sheet L1 Capability Index
A1: L1 Domain | B1: Description | C1: L2 Count | D1: Capability Function
A2: Payment Management | B2: The enterprise-wide ability to initiate, process, route, clear, settle, and reconcile all forms of monetary transactions across retail, commercial, and interbank channels. This capability encompasses ... | C2: 6 | D2: Payment Infrastructure
A3: Account Management | B3: The enterprise-wide ability to create, maintain, service, and close all types of customer accounts across retail, commercial, and institutional banking segments. This capability spans the complete acc... | C3: 5 | D3: Core Banking Systems
A4: Customer Management | B4: The enterprise-wide ability to acquire, onboard, understand, engage, serve, retain, and grow customer relationships across all segments (retail, mass affluent, HNW, SME, corporate, institutional). Thi... | C4: 4 | D4: Customer & Digital Experience
A5: Risk Management | B5: The enterprise-wide ability to identify, measure, monitor, mitigate, and report all categories of risk including credit risk, market risk, operational risk, liquidity risk, model risk, cyber risk, and... | C5: 6 | D5: Risk Management
A6: Compliance and Regulatory Management | B6: The enterprise-wide ability to ensure adherence to all applicable laws, regulations, industry standards, and internal policies across all banking operations and jurisdictions. This capability encompas... | C6: 4 | D6: Security & Compliance
A7: Treasury and Capital Markets | B7: The enterprise-wide ability to manage the bank's own balance sheet, funding, liquidity, investment portfolio, and capital markets activities. This capability encompasses asset-liability management, fu... | C7: 4 | D7: Treasury & Capital Markets
A8: Lending and Credit | B8: The enterprise-wide ability to originate, underwrite, approve, fund, and manage credit products across retail and commercial segments. This capability encompasses the complete credit lifecycle from ap... | C8: 4 | D8: Core Banking Systems
A9: Wealth and Investment Management | B9: The enterprise-wide ability to provide comprehensive wealth management, investment advisory, brokerage, trust, and private banking services to high-net-worth, ultra-high-net-worth, and affluent custom... | C9: 3 | D9: Enterprise Services
A10: Enterprise Operations | B10: The enterprise-wide ability to execute and support the bank's core operational processes including transaction processing, document management, reconciliation, exception handling, and back-office oper... | C10: 5 | D10: Internal Operations
A11: Data and Analytics | B11: The enterprise-wide ability to collect, integrate, store, govern, analyze, and derive actionable insights from structured and unstructured data across all banking domains. This capability encompasses ... | C11: 3 | D11: Data & Analytics
A12: Information Technology | B12: The enterprise-wide ability to plan, build, run, and secure the technology infrastructure, platforms, and applications that enable all banking capabilities. This encompasses IT strategy, architecture,... | C12: 4 | D12: Enterprise Services
A13: Open Banking and Partner Ecosystem | B13: The enterprise-wide ability to participate in open banking frameworks, manage third-party integrations, enable embedded finance, and orchestrate partner ecosystem relationships. This capability encomp... | C13: 4 | D13: Partner Ecosystem
... A15: Trade Finance and Supply Chain Finance | B15: The enterprise-wide ability to facilitate domestic and international trade through structured financial instruments and supply chain financing solutions. This capability encompasses letters of credit,... | C15: 3 | D15: Core Banking Systems
